astchunk/__init__.py
astchunk/astchunk.py
astchunk/astchunk_builder.py
astchunk/astnode.py
astchunk/preprocessing.py
astchunk-0.1.0.dist-info/licenses/LICENSE
astchunk-0.1.0.dist-info/METADATA
astchunk-0.1.0.dist-info/WHEEL
astchunk-0.1.0.dist-info/entry_points.txt
astchunk-0.1.0.dist-info/top_level.txt
astchunk-0.1.0.dist-info/RECORD
