Metadata-Version: 2.4
Name: astchunk
Version: 0.1.0
Summary: AST-based code chunking library for improved code analysis and processing
Author-email: "Yilin (Jason) Zhang" <jasonzh3@andrew.cmu.edu>, Xinran Zhao <xinranz3@andrew.cmu.edu>, Zora Zhiruo Wang <zhiruow@andrew.cmu.edu>, Chenyang Yang <cyang3@andrew.cmu.edu>, Jiayi Wei <jiayi@augmentcode.com>, Sherry Tongshuang Wu <sherryw@andrew.cmu.edu>
Maintainer-email: "Yilin (Jason) Zhang" <jasonzh3@andrew.cmu.edu>
License: MIT License
Project-URL: Homepage, https://github.com/yilinjz/astchunk
Keywords: ast,chunking,code analysis,code indexing,code retrieval,code generation,tree-sitter,parsing
Classifier: Development Status :: 3 - Alpha
Classifier: Intended Audience :: Science/Research
Classifier: Intended Audience :: Developers
Classifier: License :: OSI Approved :: MIT License
Classifier: Operating System :: OS Independent
Classifier: Programming Language :: Python :: 3
Classifier: Programming Language :: Python :: 3.8
Classifier: Programming Language :: Python :: 3.9
Classifier: Programming Language :: Python :: 3.10
Classifier: Programming Language :: Python :: 3.11
Classifier: Programming Language :: Python :: 3.12
Classifier: Topic :: Software Development :: Libraries :: Python Modules
Classifier: Topic :: Software Development :: Code Generators
Classifier: Topic :: Text Processing :: Linguistic
Requires-Python: >=3.8
License-File: LICENSE
Requires-Dist: numpy>=1.20.0
Requires-Dist: pyrsistent>=0.18.0
Requires-Dist: tree-sitter>=0.20.0
Requires-Dist: tree-sitter-python>=0.20.0
Requires-Dist: tree-sitter-java>=0.20.0
Requires-Dist: tree-sitter-c-sharp>=0.20.0
Requires-Dist: tree-sitter-typescript>=0.20.0
Provides-Extra: dev
Requires-Dist: pytest>=7.0.0; extra == "dev"
Requires-Dist: pytest-cov>=4.0.0; extra == "dev"
Requires-Dist: black>=22.0.0; extra == "dev"
Requires-Dist: isort>=5.10.0; extra == "dev"
Requires-Dist: flake8>=5.0.0; extra == "dev"
Requires-Dist: mypy>=1.0.0; extra == "dev"
Requires-Dist: pre-commit>=2.20.0; extra == "dev"
Provides-Extra: docs
Requires-Dist: sphinx>=5.0.0; extra == "docs"
Requires-Dist: sphinx-rtd-theme>=1.0.0; extra == "docs"
Requires-Dist: myst-parser>=0.18.0; extra == "docs"
Provides-Extra: test
Requires-Dist: pytest>=7.0.0; extra == "test"
Requires-Dist: pytest-cov>=4.0.0; extra == "test"
Requires-Dist: pytest-xdist>=2.5.0; extra == "test"
Dynamic: license-file
